richtqdm/__init__.py
richtqdm/core.py
richtqdm-0.1.3.dist-info/licenses/LICENSE
richtqdm-0.1.3.dist-info/METADATA
richtqdm-0.1.3.dist-info/WHEEL
richtqdm-0.1.3.dist-info/top_level.txt
richtqdm-0.1.3.dist-info/RECORD
