Metadata-Version: 2.4
Name: richtqdm
Version: 0.1.3
Summary: A tqdm-style progress bar using Rich
Author-email: Mahbodez <mahbodissaiy@gmail.com>
License: MIT
Project-URL: Repository, https://github.com/mahbodez/richtqdm
Project-URL: Author Profile, https://github.com/mahbodez
Requires-Python: >=3.7
License-File: LICENSE
Requires-Dist: rich<14.0.0,>=12.0.0
Dynamic: license-file
